{
    "type": "package",
    "name": "linsyking/messenger-extra",
    "summary": "Extra library for Messenger.",
    "license": "BSD-3-Clause",
    "version": "5.0.0",
    "exposed-modules": {
        "Core Extension": [
            "Messenger.Layer.LayerExtra",
            "Messenger.Component.PortableComponent",
            "Messenger.Component.InitUpdateComponent"
        ],
        "Misc": [
            "Messenger.Misc.KeyCode",
            "Messenger.Misc.RNG",
            "Messenger.Scene.VSR"
        ],
        "GlobalComponents": [
            "Messenger.GlobalComponents.FPS.Model",
            "Messenger.GlobalComponents.Transition.Model",
            "Messenger.GlobalComponents.Transition.Base",
            "Messenger.GlobalComponents.Transition.Transitions"
        ]
    },
    "elm-version": "0.19.0 <= v < 0.20.0",
    "dependencies": {
        "avh4/elm-color": "1.0.0 <= v < 2.0.0",
        "elm/core": "1.0.0 <= v < 2.0.0",
        "elm/json": "1.1.3 <= v < 2.0.0",
        "elm/random": "1.0.0 <= v < 2.0.0",
        "ianmackenzie/elm-units": "2.10.0 <= v < 3.0.0",
        "linsyking/elm-regl": "4.1.0 <= v < 5.0.0",
        "linsyking/messenger-core": "16.0.0 <= v < 17.0.0"
    },
    "test-dependencies": {}
}
